run_it/__init__.py
run_it/core.py
run_it_for_test-0.2.dist-info/METADATA
run_it_for_test-0.2.dist-info/WHEEL
run_it_for_test-0.2.dist-info/RECORD
