Metadata-Version: 2.1
Name: run-it-for-test
Version: 0.2
Summary: A decorator for marking and running example functions
License: MIT
Author: sshling
Author-email: rml0325@qq.com
Requires-Python: >=3.9,<4.0
Classifier: License :: OSI Approved :: MIT License
Classifier: Programming Language :: Python :: 3
Classifier: Programming Language :: Python :: 3.9
Classifier: Programming Language :: Python :: 3.10
Classifier: Programming Language :: Python :: 3.11
Classifier: Programming Language :: Python :: 3.12
Requires-Dist: typing-extensions (>=4.9.0,<5.0.0)
